errorify/__init__.py
errorify/errorify.py
errorify-0.0.2.dist-info/licenses/LICENSE
errorify-0.0.2.dist-info/METADATA
errorify-0.0.2.dist-info/WHEEL
errorify-0.0.2.dist-info/top_level.txt
errorify-0.0.2.dist-info/RECORD
