Metadata-Version: 2.4
Name: errorify
Version: 0.0.2
Summary: A lightweight Python package for structured and readable exception details.
Home-page: https://github.com/bipni/Errorify
Author: Bipu Mirza
Author-email: bipumirja@gmail.com
License: MIT
Project-URL: Bug Tracker, https://github.com/bipni/Errorify/issues
Classifier: Programming Language :: Python :: 3
Classifier: License :: OSI Approved :: MIT License
Classifier: Operating System :: OS Independent
Classifier: Intended Audience :: Developers
Classifier: Topic :: Software Development :: Debuggers
Classifier: Topic :: System :: Logging
Requires-Python: >=3.8
License-File: LICENSE
Dynamic: author
Dynamic: author-email
Dynamic: classifier
Dynamic: description
Dynamic: description-content-type
Dynamic: home-page
Dynamic: license
Dynamic: license-file
Dynamic: project-url
Dynamic: requires-python
Dynamic: summary
